juham_priceforecast/__init__.py
juham_priceforecast/priceforecast.py
juham_priceforecast-0.0.1.dist-info/METADATA
juham_priceforecast-0.0.1.dist-info/WHEEL
juham_priceforecast-0.0.1.dist-info/entry_points.txt
juham_priceforecast-0.0.1.dist-info/top_level.txt
juham_priceforecast-0.0.1.dist-info/RECORD
