Metadata-Version: 2.1
Name: juham_priceforecast
Version: 0.0.1
Summary: Energy price forecast plugin for `juham` home automation applications
Author-email: J Meskanen <juham.api@gmail.com>
Maintainer-email: "J. Meskanen" <juham.api@gmail.com>
License: MIT License
Project-URL: Homepage, https://meskanen.com
Project-URL: Bug Reports, https://meskanen.com
Project-URL: Funding, https://meskanen.com
Project-URL: Say Thanks!, http://meskanen.com
Project-URL: Source, https://meskanen.com
Keywords: object-oriented,plugin,framework
Classifier: Development Status :: 1 - Planning
Classifier: Intended Audience :: Developers
Classifier: Topic :: Software Development
Classifier: License :: OSI Approved :: MIT License
Classifier: Programming Language :: Python :: 3.8
Requires-Python: >=3.8
Requires-Dist: juham >=0.0.7
Requires-Dist: pytz >=2024.1
Requires-Dist: importlib-metadata
Requires-Dist: pvlib >=0.11
Provides-Extra: dev
Requires-Dist: check-manifest ; extra == 'dev'
